{
	"Index":2838,
	"Name":"12n_0749",
	"RolfsenName":"12n_0749",
	"DTname":"12n_0749",
	"Status":"initialized*Just",
	"Diagram":{
		"Scode":"{6, 10, 14, 19, 2, 21, 4, -22, -24, 7, 11, -16}",
		"Acode":"{4, 6, 8, 11, 2, 12, 3, -12, -1, 4, 6, -9}",
		"PDcode":[
			"{1, 7, 2, 6}",
			"{3, 11, 4, 10}",
			"{5, 15, 6, 14}",
			"{18, 8, 19, 7}",
			"{9, 3, 10, 2}",
			"{20, 12, 21, 11}",
			"{13, 5, 14, 4}",
			"{15, 22, 16, 23}",
			"{17, 24, 18, 1}",
			"{8, 20, 9, 19}",
			"{12, 22, 13, 21}",
			"{23, 16, 24, 17}"
		],
		"CBtype":"{3, 0}",
		"ParabolicReps":{
			"SolvingSeq":[
				"{8, 12, 4}",
				[],
				[
					"{8, -12, 9, 1}",
					"{12, -9, 1, 1}",
					"{9, -1, 10, 1}",
					"{4, 8, 3, 2}",
					"{8, 3, 7, 2}",
					"{7, 12, 6, 2}",
					"{3, 6, 2, 2}",
					"{6, 2, 5, 2}",
					"{12, 6, 11, 2}"
				],
				"{1, 10}",
				"{4}",
				4
			],
			"SolvingSeqIdx":1,
			"Comps":{
				"u":{
					"CheckEq":[
						"-a - 2*b + a*b^2 + b^3 + u - a^2*u + a*b*u - a*u^2 - b*u^2 + 2*a^2*b*u^2 + 4*a*b^2*u^2 - a^3*b^2*u^2 + 2*b^3*u^2 - 3*a^2*b^3*u^2 - 3*a*b^4*u^2 - b^5*u^2 + a^2*u^3",
						"-b + b^3 + u - a*b*u + b^2*u + b*u^2 - a^2*b^3*u^2 - 2*a*b^4*u^2 - b^5*u^2 - u^3 + a*b*u^3 + a*u^4 + b*u^4 - 2*a^2*b*u^4 - 4*a*b^2*u^4 + a^3*b^2*u^4 - 2*b^3*u^4 + 3*a^2*b^3*u^4 + 3*a*b^4*u^4 + b^5*u^4",
						"1 + a*b - u + 2*a*b*u + 2*b^2*u - a^2*b^2*u - 2*a*b^3*u - b^4*u - u^2 + 2*a^2*u^2 - a*b*u^2 - a^2*u^4",
						"b^2 - u + b^2*u - a*b^3*u - b^4*u - 2*u^2 + 2*a*b*u^2 - b^2*u^2 + u^3 - 2*a*b*u^3 - 2*b^2*u^3 + a^2*b^2*u^3 + 2*a*b^3*u^3 + b^4*u^3 + u^4 - a*b*u^4"
					],
					"TimingForPrimaryIdeals":0.149579
				},
				"v":{
					"CheckEq":[
						"b^2 + b^4*v",
						"-b + b^3 + b^2*v - b^5*v^2",
						"1 + a*b - v - b^2*v + a*b^3*v + b^4*v + b^4*v^3",
						"-a - 2*b + a*b^2 + b^3 + v + a*b*v + 2*b^3*v^2 - a*b^4*v^2 - b^5*v^2 - b^5*v^4"
					],
					"TimingForPrimaryIdeals":9.659700000000003e-2
				},
				"PrimaryIdeals":[
					{
						"IdealName":"J12n_749_0",
						"Generators":[
							"-1 + b + u + 8*u^2 + 6*u^3 - 5*u^4 - 5*u^5 + u^6 + u^7",
							"2 + a - u - 8*u^2 - 6*u^3 + 5*u^4 + 5*u^5 - u^6 - u^7",
							"1 - 5*u - 5*u^2 + 15*u^3 + 22*u^4 - 3*u^5 - 15*u^6 - 3*u^7 + 3*u^8 + u^9"
						],
						"VariableOrder":[
							"b",
							"a",
							"u"
						],
						"Characteristic":0,
						"KnownGroebner":[],
						"Status":[
							"vCompNormalize"
						],
						"MonomialOrder":"lex",
						"IsHomogeneous":false,
						"IsZeroDim":true,
						"IdealDimension":0,
						"Timings":{
							"TimingGroebner":0.16433,
							"TimingZeroDimVars":0.488091,
							"TimingmagmaVCompNormalize":0.489313,
							"TimingNumberOfSols":0.321733,
							"TimingIsRadical":2.2332e-2,
							"TimingArcColoring":0.776326,
							"TimingObstruction":1.252e-2,
							"TimingComplexVolumeN":8.687541,
							"TimingaCuspShapeN":4.565e-2,
							"TiminguValues":0.789803,
							"TiminguPolysN":8.814e-3,
							"TiminguPolys":1.009643,
							"TimingaCuspShape":0.120405,
							"TimingRepresentationsN":7.6554e-2,
							"TiminguValues_ij":1.337364,
							"TiminguPoly_ij":4.349449,
							"TiminguPolys_ij_N":2.6417000000000003e-2
						},
						"ZeroDimensionalVars":[
							"b",
							"a",
							"u"
						],
						"NumberOfSols":9,
						"IsRadical":true,
						"ArcColoring":[
							[
								"u",
								"u - u^3"
							],
							[
								"-2*u - u^2 + 8*u^3 + 7*u^4 - 5*u^5 - 5*u^6 + u^7 + u^8",
								"-2 + 12*u + 8*u^2 - 26*u^3 - 25*u^4 + 15*u^5 + 16*u^6 - 3*u^7 - 3*u^8"
							],
							[
								-1,
								"1 - u - 8*u^2 - 6*u^3 + 5*u^4 + 5*u^5 - u^6 - u^7"
							],
							[
								"-2 + u + 8*u^2 + 6*u^3 - 5*u^4 - 5*u^5 + u^6 + u^7",
								"1 - u - 8*u^2 - 6*u^3 + 5*u^4 + 5*u^5 - u^6 - u^7"
							],
							[
								"6 - 22*u - 17*u^2 + 54*u^3 + 56*u^4 - 33*u^5 - 37*u^6 + 7*u^7 + 7*u^8",
								"-2 + 8*u + 5*u^2 - 19*u^3 - 17*u^4 + 13*u^5 + 11*u^6 - 3*u^7 - 2*u^8"
							],
							[
								"2 - u - 8*u^2 - 6*u^3 + 5*u^4 + 5*u^5 - u^6 - u^7",
								"-6*u^2 - 11*u^3 - 2*u^4 + 9*u^5 + 4*u^6 - 2*u^7 - u^8"
							],
							[
								"2 - u - 8*u^2 - 6*u^3 + 5*u^4 + 5*u^5 - u^6 - u^7",
								"1 - 5*u - 9*u^2 + 3*u^3 + 12*u^4 - 6*u^6 + u^8"
							],
							"{1, 0}",
							[
								1,
								"-u^2"
							],
							[
								"1 - u^2",
								"-2*u^2 + u^4"
							],
							[
								"1 - 3*u - 2*u^2 + 8*u^3 + 7*u^4 - 5*u^5 - 5*u^6 + u^7 + u^8",
								"-2 + 11*u + 6*u^2 - 25*u^3 - 24*u^4 + 15*u^5 + 16*u^6 - 3*u^7 - 3*u^8"
							],
							[
								0,
								"u"
							]
						],
						"Obstruction":-1,
						"ComplexVolumeN":[
							"1.43676 - 1.39156*I",
							"1.43676 + 1.39156*I",
							-1.87529,
							-8.12479,
							"9.69068 + 4.28297*I",
							"9.69068 - 4.28297*I",
							-0.677543,
							"-16.4807 - 5.9861*I",
							"-16.4807 + 5.9861*I"
						],
						"uPolysN":[
							"-1 - 2*u - 4*u^2 - 13*u^3 + 3*u^4 - 15*u^5 + 15*u^6 + 18*u^7 - u^8 + u^9",
							"1 - 7*u + 10*u^2 + 30*u^3 - 72*u^4 + 42*u^5 - 31*u^6 + 15*u^7 + u^9",
							"8 - 20*u + 8*u^2 + 57*u^3 - 132*u^4 + 144*u^5 - 94*u^6 + 38*u^7 - 9*u^8 + u^9",
							"-1 - 2*u - 4*u^2 - 13*u^3 + 3*u^4 - 15*u^5 + 15*u^6 + 18*u^7 - u^8 + u^9",
							"1 - 7*u + 10*u^2 + 30*u^3 - 72*u^4 + 42*u^5 - 31*u^6 + 15*u^7 + u^9",
							"-1 - u + 11*u^2 + 8*u^3 + 14*u^4 + 39*u^5 + 4*u^6 + 12*u^7 + 2*u^8 + u^9",
							"8 - 20*u + 8*u^2 + 57*u^3 - 132*u^4 + 144*u^5 - 94*u^6 + 38*u^7 - 9*u^8 + u^9",
							"-1 - 5*u + 5*u^2 + 15*u^3 - 22*u^4 - 3*u^5 + 15*u^6 - 3*u^7 - 3*u^8 + u^9",
							"-1 - 5*u + 5*u^2 + 15*u^3 - 22*u^4 - 3*u^5 + 15*u^6 - 3*u^7 - 3*u^8 + u^9",
							"-1 - 2*u - 4*u^2 - 13*u^3 + 3*u^4 - 15*u^5 + 15*u^6 + 18*u^7 - u^8 + u^9",
							"-1 - u + 11*u^2 + 8*u^3 + 14*u^4 + 39*u^5 + 4*u^6 + 12*u^7 + 2*u^8 + u^9",
							"-1 - 5*u + 5*u^2 + 15*u^3 - 22*u^4 - 3*u^5 + 15*u^6 - 3*u^7 - 3*u^8 + u^9"
						],
						"uPolys":[
							"-1 - 2*u - 4*u^2 - 13*u^3 + 3*u^4 - 15*u^5 + 15*u^6 + 18*u^7 - u^8 + u^9",
							"1 - 7*u + 10*u^2 + 30*u^3 - 72*u^4 + 42*u^5 - 31*u^6 + 15*u^7 + u^9",
							"8 - 20*u + 8*u^2 + 57*u^3 - 132*u^4 + 144*u^5 - 94*u^6 + 38*u^7 - 9*u^8 + u^9",
							"-1 - 2*u - 4*u^2 - 13*u^3 + 3*u^4 - 15*u^5 + 15*u^6 + 18*u^7 - u^8 + u^9",
							"1 - 7*u + 10*u^2 + 30*u^3 - 72*u^4 + 42*u^5 - 31*u^6 + 15*u^7 + u^9",
							"-1 - u + 11*u^2 + 8*u^3 + 14*u^4 + 39*u^5 + 4*u^6 + 12*u^7 + 2*u^8 + u^9",
							"8 - 20*u + 8*u^2 + 57*u^3 - 132*u^4 + 144*u^5 - 94*u^6 + 38*u^7 - 9*u^8 + u^9",
							"-1 - 5*u + 5*u^2 + 15*u^3 - 22*u^4 - 3*u^5 + 15*u^6 - 3*u^7 - 3*u^8 + u^9",
							"-1 - 5*u + 5*u^2 + 15*u^3 - 22*u^4 - 3*u^5 + 15*u^6 - 3*u^7 - 3*u^8 + u^9",
							"-1 - 2*u - 4*u^2 - 13*u^3 + 3*u^4 - 15*u^5 + 15*u^6 + 18*u^7 - u^8 + u^9",
							"-1 - u + 11*u^2 + 8*u^3 + 14*u^4 + 39*u^5 + 4*u^6 + 12*u^7 + 2*u^8 + u^9",
							"-1 - 5*u + 5*u^2 + 15*u^3 - 22*u^4 - 3*u^5 + 15*u^6 - 3*u^7 - 3*u^8 + u^9"
						],
						"aCuspShape":"-17 - 4*u + 62*u^2 + 73*u^3 - 23*u^4 - 54*u^5 - 6*u^6 + 11*u^7 + 3*u^8",
						"RepresentationsN":[
							[
								"u->-0.803718 + 0.480044 I",
								"a->-0.545358 + 0.558768 I",
								"b->-0.454642 - 0.558768 I"
							],
							[
								"u->-0.803718 - 0.480044 I",
								"a->-0.545358 - 0.558768 I",
								"b->-0.454642 + 0.558768 I"
							],
							[
								"u->-1.39574",
								"a->0.458311",
								"b->-1.45831"
							],
							[
								"u->0.479009",
								"a->0.602594",
								"b->-1.60259"
							],
							[
								"u->1.5629 + 0.23534 I",
								"a->0.115329 - 1.18452 I",
								"b->-1.11533 + 1.18452 I"
							],
							[
								"u->1.5629 - 0.23534 I",
								"a->0.115329 + 1.18452 I",
								"b->-1.11533 - 1.18452 I"
							],
							[
								"u->0.189912",
								"a->-1.48814",
								"b->0.488141"
							],
							[
								"u->-1.89577 + 0.05938 I",
								"a->0.64365 + 1.55034 I",
								"b->-1.64365 - 1.55034 I"
							],
							[
								"u->-1.89577 - 0.05938 I",
								"a->0.64365 - 1.55034 I",
								"b->-1.64365 + 1.55034 I"
							]
						],
						"Epsilon":1.79446,
						"uPolys_ij":[
							"-1 - 5*u + 5*u^2 + 15*u^3 - 22*u^4 - 3*u^5 + 15*u^6 - 3*u^7 - 3*u^8 + u^9",
							"-1 + 35*u - 219*u^2 + 505*u^3 - 700*u^4 + 599*u^5 - 309*u^6 + 93*u^7 - 15*u^8 + u^9",
							"11 + 73*u + 24*u^2 - 244*u^3 + 86*u^4 + 158*u^5 - 47*u^6 - 9*u^7 + 6*u^8 + u^9",
							"-1 + 27*u - 213*u^2 + 455*u^3 - 224*u^4 + 77*u^5 - 23*u^6 + 13*u^7 + 9*u^8 + u^9",
							"1 - 4*u - 42*u^2 + 283*u^3 - 427*u^4 - 345*u^5 + 785*u^6 + 324*u^7 - 35*u^8 + u^9",
							"296 + 1552*u + 1906*u^2 - 871*u^3 - 2153*u^4 + 196*u^5 + 1258*u^6 + 360*u^7 - 38*u^8 + u^9",
							"64 + 928*u - 3420*u^2 + 2965*u^3 + 911*u^4 - 2928*u^5 - 664*u^6 + 282*u^7 + 32*u^8 + u^9",
							"8 - 20*u + 8*u^2 + 57*u^3 - 132*u^4 + 144*u^5 - 94*u^6 + 38*u^7 - 9*u^8 + u^9",
							"823 - 1413*u - 1957*u^2 + 7078*u^3 - 7584*u^4 + 4177*u^5 - 1320*u^6 + 242*u^7 - 24*u^8 + u^9",
							"23 - 1128*u - 2442*u^2 - 653*u^3 - 11436*u^4 + 8267*u^5 - 12350*u^6 + 8745*u^7 - 99*u^8 + u^9",
							"1829 - 7400*u + 3698*u^2 + 47147*u^3 - 93480*u^4 + 40556*u^5 - 30350*u^6 + 7588*u^7 - 98*u^8 + u^9",
							"-21841 - 156773*u + 143330*u^2 - 75034*u^3 + 610*u^4 + 19246*u^5 - 5219*u^6 + 677*u^7 - 24*u^8 + u^9",
							"-11072 - 17312*u + 61776*u^2 + 2592*u^3 - 53540*u^4 + 10272*u^5 - 187*u^6 + 328*u^7 - 9*u^8 + u^9",
							"-29 - 112*u + 225*u^2 - 372*u^3 + 286*u^4 - 79*u^5 - 26*u^6 + 58*u^7 + u^8 + u^9",
							"-73 + 1006*u - 3803*u^2 - 5290*u^3 + 22012*u^4 + 2069*u^5 - 4706*u^6 + 1424*u^7 - 71*u^8 + u^9",
							"-1 - 29*u - 151*u^2 + 784*u^3 - 1355*u^4 + 1162*u^5 - 481*u^6 + 58*u^7 + 11*u^8 + u^9",
							"-31 + 5*u + 205*u^2 - 448*u^3 - 383*u^4 + 166*u^5 - 91*u^6 + 48*u^7 - u^8 + u^9",
							"-1 - 2*u - 4*u^2 - 13*u^3 + 3*u^4 - 15*u^5 + 15*u^6 + 18*u^7 - u^8 + u^9",
							"1 - 3*u - 8*u^2 + 42*u^3 - 30*u^4 - 24*u^5 + 29*u^6 - 3*u^7 - 4*u^8 + u^9",
							"-151 - 558*u - 34*u^2 + 1185*u^3 + 312*u^4 - 1322*u^5 - 246*u^6 + 244*u^7 + 28*u^8 + u^9",
							"-631 - 4215*u + 6904*u^2 - 6328*u^3 - 3820*u^4 + 5022*u^5 - 1287*u^6 + 13*u^7 + 16*u^8 + u^9",
							"64 + 272*u + 232*u^2 + 1105*u^3 + 880*u^4 + 356*u^5 + 154*u^6 + 40*u^7 + 5*u^8 + u^9",
							"1 + 29*u + 376*u^2 + 1814*u^3 + 2254*u^4 - 1814*u^5 - 359*u^6 + 309*u^7 - 30*u^8 + u^9",
							"3512 + 3908*u - 14376*u^2 + 4799*u^3 + 8590*u^4 - 1842*u^5 - 642*u^6 + 237*u^7 - 24*u^8 + u^9",
							"-1 - u + 11*u^2 + 8*u^3 + 14*u^4 + 39*u^5 + 4*u^6 + 12*u^7 + 2*u^8 + u^9",
							"-23 + 148*u - 11*u^2 - 2076*u^3 + 3782*u^4 + 355*u^5 - 444*u^6 - 22*u^7 + 11*u^8 + u^9",
							"-1579 - 2997*u + 8147*u^2 + 2066*u^3 - 9325*u^4 + 1218*u^5 + 1283*u^6 + 50*u^7 - 17*u^8 + u^9",
							"1 + 23*u + 109*u^2 - 314*u^3 - 320*u^4 + 1555*u^5 - 880*u^6 + 206*u^7 - 20*u^8 + u^9",
							"-1081 - 1832*u + 3252*u^2 + 1954*u^3 - 2181*u^4 - 857*u^5 + 288*u^6 + 179*u^7 + 24*u^8 + u^9",
							"1 - 7*u + 10*u^2 + 30*u^3 - 72*u^4 + 42*u^5 - 31*u^6 + 15*u^7 + u^9",
							"7331 + 46763*u + 46292*u^2 + 48852*u^3 + 28650*u^4 + 8098*u^5 + 1501*u^6 + 221*u^7 + 14*u^8 + u^9",
							"-173 - 1486*u + 1222*u^2 + 451*u^3 - 1002*u^4 + 126*u^5 - 46*u^6 + 56*u^7 + u^9",
							"-47 + 43*u + 211*u^2 - 554*u^3 + 509*u^4 - 82*u^5 - 117*u^6 + 64*u^7 - 3*u^8 + u^9",
							"-2581 - 4949*u + 40285*u^2 + 63664*u^3 - 44798*u^4 + 86947*u^5 - 7494*u^6 + 596*u^7 + 54*u^8 + u^9",
							"13037 - 10096*u - 35262*u^2 + 82301*u^3 - 59119*u^4 + 9829*u^5 + 167*u^6 + 1466*u^7 + 69*u^8 + u^9",
							"-1153 - 979*u + 4892*u^2 - 2798*u^3 + 40525*u^4 + 31409*u^5 - 2550*u^6 + 2173*u^7 + 79*u^8 + u^9",
							"-1903 + 12651*u - 3554*u^2 - 119616*u^3 + 146995*u^4 + 132167*u^5 + 10300*u^6 + 4755*u^7 + 93*u^8 + u^9",
							"-2507 - 595*u + 8423*u^2 + 61203*u^3 + 228688*u^4 + 80667*u^5 + 21503*u^6 + 5093*u^7 + 93*u^8 + u^9",
							"168251 - 130347*u - 2015083*u^2 + 4177277*u^3 + 6933575*u^4 + 1087662*u^5 - 381508*u^6 + 27497*u^7 - 86*u^8 + u^9"
						],
						"GeometricComponent":"{8, 9}",
						"uPolys_ij_N":[
							"-1 - 5*u + 5*u^2 + 15*u^3 - 22*u^4 - 3*u^5 + 15*u^6 - 3*u^7 - 3*u^8 + u^9",
							"-1 + 35*u - 219*u^2 + 505*u^3 - 700*u^4 + 599*u^5 - 309*u^6 + 93*u^7 - 15*u^8 + u^9",
							"11 + 73*u + 24*u^2 - 244*u^3 + 86*u^4 + 158*u^5 - 47*u^6 - 9*u^7 + 6*u^8 + u^9",
							"-1 + 27*u - 213*u^2 + 455*u^3 - 224*u^4 + 77*u^5 - 23*u^6 + 13*u^7 + 9*u^8 + u^9",
							"1 - 4*u - 42*u^2 + 283*u^3 - 427*u^4 - 345*u^5 + 785*u^6 + 324*u^7 - 35*u^8 + u^9",
							"296 + 1552*u + 1906*u^2 - 871*u^3 - 2153*u^4 + 196*u^5 + 1258*u^6 + 360*u^7 - 38*u^8 + u^9",
							"64 + 928*u - 3420*u^2 + 2965*u^3 + 911*u^4 - 2928*u^5 - 664*u^6 + 282*u^7 + 32*u^8 + u^9",
							"8 - 20*u + 8*u^2 + 57*u^3 - 132*u^4 + 144*u^5 - 94*u^6 + 38*u^7 - 9*u^8 + u^9",
							"823 - 1413*u - 1957*u^2 + 7078*u^3 - 7584*u^4 + 4177*u^5 - 1320*u^6 + 242*u^7 - 24*u^8 + u^9",
							"23 - 1128*u - 2442*u^2 - 653*u^3 - 11436*u^4 + 8267*u^5 - 12350*u^6 + 8745*u^7 - 99*u^8 + u^9",
							"1829 - 7400*u + 3698*u^2 + 47147*u^3 - 93480*u^4 + 40556*u^5 - 30350*u^6 + 7588*u^7 - 98*u^8 + u^9",
							"-21841 - 156773*u + 143330*u^2 - 75034*u^3 + 610*u^4 + 19246*u^5 - 5219*u^6 + 677*u^7 - 24*u^8 + u^9",
							"-11072 - 17312*u + 61776*u^2 + 2592*u^3 - 53540*u^4 + 10272*u^5 - 187*u^6 + 328*u^7 - 9*u^8 + u^9",
							"-29 - 112*u + 225*u^2 - 372*u^3 + 286*u^4 - 79*u^5 - 26*u^6 + 58*u^7 + u^8 + u^9",
							"-73 + 1006*u - 3803*u^2 - 5290*u^3 + 22012*u^4 + 2069*u^5 - 4706*u^6 + 1424*u^7 - 71*u^8 + u^9",
							"-1 - 29*u - 151*u^2 + 784*u^3 - 1355*u^4 + 1162*u^5 - 481*u^6 + 58*u^7 + 11*u^8 + u^9",
							"-31 + 5*u + 205*u^2 - 448*u^3 - 383*u^4 + 166*u^5 - 91*u^6 + 48*u^7 - u^8 + u^9",
							"-1 - 2*u - 4*u^2 - 13*u^3 + 3*u^4 - 15*u^5 + 15*u^6 + 18*u^7 - u^8 + u^9",
							"1 - 3*u - 8*u^2 + 42*u^3 - 30*u^4 - 24*u^5 + 29*u^6 - 3*u^7 - 4*u^8 + u^9",
							"-151 - 558*u - 34*u^2 + 1185*u^3 + 312*u^4 - 1322*u^5 - 246*u^6 + 244*u^7 + 28*u^8 + u^9",
							"-631 - 4215*u + 6904*u^2 - 6328*u^3 - 3820*u^4 + 5022*u^5 - 1287*u^6 + 13*u^7 + 16*u^8 + u^9",
							"64 + 272*u + 232*u^2 + 1105*u^3 + 880*u^4 + 356*u^5 + 154*u^6 + 40*u^7 + 5*u^8 + u^9",
							"1 + 29*u + 376*u^2 + 1814*u^3 + 2254*u^4 - 1814*u^5 - 359*u^6 + 309*u^7 - 30*u^8 + u^9",
							"3512 + 3908*u - 14376*u^2 + 4799*u^3 + 8590*u^4 - 1842*u^5 - 642*u^6 + 237*u^7 - 24*u^8 + u^9",
							"-1 - u + 11*u^2 + 8*u^3 + 14*u^4 + 39*u^5 + 4*u^6 + 12*u^7 + 2*u^8 + u^9",
							"-23 + 148*u - 11*u^2 - 2076*u^3 + 3782*u^4 + 355*u^5 - 444*u^6 - 22*u^7 + 11*u^8 + u^9",
							"-1579 - 2997*u + 8147*u^2 + 2066*u^3 - 9325*u^4 + 1218*u^5 + 1283*u^6 + 50*u^7 - 17*u^8 + u^9",
							"1 + 23*u + 109*u^2 - 314*u^3 - 320*u^4 + 1555*u^5 - 880*u^6 + 206*u^7 - 20*u^8 + u^9",
							"-1081 - 1832*u + 3252*u^2 + 1954*u^3 - 2181*u^4 - 857*u^5 + 288*u^6 + 179*u^7 + 24*u^8 + u^9",
							"1 - 7*u + 10*u^2 + 30*u^3 - 72*u^4 + 42*u^5 - 31*u^6 + 15*u^7 + u^9",
							"7331 + 46763*u + 46292*u^2 + 48852*u^3 + 28650*u^4 + 8098*u^5 + 1501*u^6 + 221*u^7 + 14*u^8 + u^9",
							"-173 - 1486*u + 1222*u^2 + 451*u^3 - 1002*u^4 + 126*u^5 - 46*u^6 + 56*u^7 + u^9",
							"-47 + 43*u + 211*u^2 - 554*u^3 + 509*u^4 - 82*u^5 - 117*u^6 + 64*u^7 - 3*u^8 + u^9",
							"-2581 - 4949*u + 40285*u^2 + 63664*u^3 - 44798*u^4 + 86947*u^5 - 7494*u^6 + 596*u^7 + 54*u^8 + u^9",
							"13037 - 10096*u - 35262*u^2 + 82301*u^3 - 59119*u^4 + 9829*u^5 + 167*u^6 + 1466*u^7 + 69*u^8 + u^9",
							"-1153 - 979*u + 4892*u^2 - 2798*u^3 + 40525*u^4 + 31409*u^5 - 2550*u^6 + 2173*u^7 + 79*u^8 + u^9",
							"-1903 + 12651*u - 3554*u^2 - 119616*u^3 + 146995*u^4 + 132167*u^5 + 10300*u^6 + 4755*u^7 + 93*u^8 + u^9",
							"-2507 - 595*u + 8423*u^2 + 61203*u^3 + 228688*u^4 + 80667*u^5 + 21503*u^6 + 5093*u^7 + 93*u^8 + u^9",
							"168251 - 130347*u - 2015083*u^2 + 4177277*u^3 + 6933575*u^4 + 1087662*u^5 - 381508*u^6 + 27497*u^7 - 86*u^8 + u^9"
						],
						"Multiplicity":1,
						"ij_list":[
							[
								"{1, 9}",
								"{1, 10}",
								"{2, 11}",
								"{3, 12}",
								"{8, 12}",
								"{9, 12}"
							],
							[
								"{1, 12}",
								"{8, 9}",
								"{9, 10}"
							],
							[
								"{1, 8}",
								"{10, 12}"
							],
							[
								"{8, 10}"
							],
							[
								"{1, 2}",
								"{4, 5}",
								"{10, 11}"
							],
							[
								"{2, 10}"
							],
							[
								"{1, 11}"
							],
							[
								"{3, 7}",
								"{3, 8}",
								"{4, 8}"
							],
							[
								"{3, 9}"
							],
							[
								"{5, 10}"
							],
							[
								"{1, 5}"
							],
							[
								"{7, 10}"
							],
							[
								"{1, 7}"
							],
							[
								"{6, 10}"
							],
							[
								"{5, 8}"
							],
							[
								"{2, 12}"
							],
							[
								"{1, 6}"
							],
							[
								"{1, 4}",
								"{2, 4}",
								"{4, 10}",
								"{4, 11}",
								"{5, 11}"
							],
							[
								"{4, 6}",
								"{6, 8}"
							],
							[
								"{2, 9}"
							],
							[
								"{9, 11}"
							],
							[
								"{3, 4}",
								"{6, 9}",
								"{7, 8}"
							],
							[
								"{2, 3}",
								"{5, 6}"
							],
							[
								"{4, 7}"
							],
							[
								"{4, 12}",
								"{6, 11}",
								"{6, 12}",
								"{7, 12}"
							],
							[
								"{1, 3}"
							],
							[
								"{3, 11}"
							],
							[
								"{6, 7}",
								"{11, 12}"
							],
							[
								"{3, 10}"
							],
							[
								"{2, 5}",
								"{2, 6}",
								"{3, 6}",
								"{4, 9}"
							],
							[
								"{7, 9}"
							],
							[
								"{8, 11}"
							],
							[
								"{2, 8}"
							],
							[
								"{7, 11}"
							],
							[
								"{2, 7}"
							],
							[
								"{5, 12}"
							],
							[
								"{3, 5}"
							],
							[
								"{5, 9}"
							],
							[
								"{5, 7}"
							]
						],
						"SortedReprnIndices":"{9, 8, 5, 6, 2, 1, 4, 3, 7}",
						"aCuspShapeN":[
							"-1.6715555537063892599`4.640189988998639 + 5.1485457241203744485`5.128753748222637*I",
							"-1.6715555537063892599`4.640189988998639 - 5.1485457241203744485`5.128753748222637*I",
							-5.0364,
							0.75995,
							"-4.6499843358135090211`5.07675731431023 - 2.9573292753015681491`4.880205506890717*I",
							"-4.6499843358135090211`5.07675731431023 + 2.9573292753015681491`4.880205506890717*I",
							-1.5067e1,
							"-4.5067706495260753513`5.116431165900017 + 1.8579211906986847797`4.7315929967460315*I",
							"-4.5067706495260753513`5.116431165900017 - 1.8579211906986847797`4.7315929967460315*I"
						],
						"Abelian":false
					},
					{
						"IdealName":"J12n_749_1",
						"Generators":[
							"-2 + b - u + 3*u^2 + u^3 - u^4",
							"3 + a + u - 3*u^2 - u^3 + u^4",
							"-1 - 3*u + 4*u^2 + 5*u^3 - 3*u^4 - 2*u^5 + u^6"
						],
						"VariableOrder":[
							"b",
							"a",
							"u"
						],
						"Characteristic":0,
						"KnownGroebner":[],
						"Status":[
							"vCompNormalize"
						],
						"MonomialOrder":"lex",
						"IsHomogeneous":false,
						"IsZeroDim":true,
						"IdealDimension":0,
						"Timings":{
							"TimingGroebner":0.171013,
							"TimingZeroDimVars":0.478542,
							"TimingmagmaVCompNormalize":0.479878,
							"TimingNumberOfSols":0.295446,
							"TimingIsRadical":2.3459e-2,
							"TimingArcColoring":0.753014,
							"TimingObstruction":6.211e-3,
							"TimingComplexVolumeN":6.046829,
							"TimingaCuspShapeN":2.9874e-2,
							"TiminguValues":0.792154,
							"TiminguPolysN":3.533e-3,
							"TiminguPolys":0.989496,
							"TimingaCuspShape":0.108036,
							"TimingRepresentationsN":5.5992e-2,
							"TiminguValues_ij":1.334562,
							"TiminguPoly_ij":4.451666,
							"TiminguPolys_ij_N":1.0962000000000001e-2
						},
						"ZeroDimensionalVars":[
							"b",
							"a",
							"u"
						],
						"NumberOfSols":6,
						"IsRadical":true,
						"ArcColoring":[
							[
								"u",
								"u - u^3"
							],
							[
								"2 - 3*u - 5*u^2 + 3*u^3 + 2*u^4 - u^5",
								"-1 + 4*u + 2*u^2 - 4*u^3 - u^4 + u^5"
							],
							[
								-1,
								"2 + u - 3*u^2 - u^3 + u^4"
							],
							[
								"-3 - u + 3*u^2 + u^3 - u^4",
								"2 + u - 3*u^2 - u^3 + u^4"
							],
							[
								"3*u + u^2 - 3*u^3 - u^4 + u^5",
								"-1 - 4*u + 6*u^3 + u^4 - 2*u^5"
							],
							[
								"3 + u - 3*u^2 - u^3 + u^4",
								"-3 - u + 3*u^2 + u^3 - u^4"
							],
							[
								"3 + u - 3*u^2 - u^3 + u^4",
								"-2 + 2*u + 2*u^2 - 3*u^3 - u^4 + u^5"
							],
							"{1, 0}",
							[
								1,
								"-u^2"
							],
							[
								"1 - u^2",
								"-2*u^2 + u^4"
							],
							[
								"-1 + 4*u + 4*u^2 - 3*u^3 - 2*u^4 + u^5",
								"1 - 3*u - 4*u^2 + 3*u^3 + 2*u^4 - u^5"
							],
							[
								0,
								"u"
							]
						],
						"Obstruction":1,
						"ComplexVolumeN":[
							"1.07088 - 0.298492*I",
							"1.07088 + 0.298492*I",
							-5.05469,
							-8.45292,
							"12.2627 + 2.92755*I",
							"12.2627 - 2.92755*I"
						],
						"uPolysN":[
							"-1 + 4*u - 3*u^2 - 4*u^3 + 2*u^4 + u^6",
							"-1 + 5*u - 5*u^2 + 2*u^4 - u^5 + u^6",
							"1 - 2*u + 4*u^3 - 2*u^4 - u^5 + u^6",
							"-1 + 4*u - 3*u^2 - 4*u^3 + 2*u^4 + u^6",
							"-1 - 5*u - 5*u^2 + 2*u^4 + u^5 + u^6",
							"-1 - 3*u - 4*u^2 - 2*u^3 + u^4 + u^5 + u^6",
							"1 + 2*u - 4*u^3 - 2*u^4 + u^5 + u^6",
							"-1 - 3*u + 4*u^2 + 5*u^3 - 3*u^4 - 2*u^5 + u^6",
							"-1 - 3*u + 4*u^2 + 5*u^3 - 3*u^4 - 2*u^5 + u^6",
							"-1 - 4*u - 3*u^2 + 4*u^3 + 2*u^4 + u^6",
							"-1 + 3*u - 4*u^2 + 2*u^3 + u^4 - u^5 + u^6",
							"-1 + 3*u + 4*u^2 - 5*u^3 - 3*u^4 + 2*u^5 + u^6"
						],
						"uPolys":[
							"-1 + 4*u - 3*u^2 - 4*u^3 + 2*u^4 + u^6",
							"-1 + 5*u - 5*u^2 + 2*u^4 - u^5 + u^6",
							"1 - 2*u + 4*u^3 - 2*u^4 - u^5 + u^6",
							"-1 + 4*u - 3*u^2 - 4*u^3 + 2*u^4 + u^6",
							"-1 - 5*u - 5*u^2 + 2*u^4 + u^5 + u^6",
							"-1 - 3*u - 4*u^2 - 2*u^3 + u^4 + u^5 + u^6",
							"1 + 2*u - 4*u^3 - 2*u^4 + u^5 + u^6",
							"-1 - 3*u + 4*u^2 + 5*u^3 - 3*u^4 - 2*u^5 + u^6",
							"-1 - 3*u + 4*u^2 + 5*u^3 - 3*u^4 - 2*u^5 + u^6",
							"-1 - 4*u - 3*u^2 + 4*u^3 + 2*u^4 + u^6",
							"-1 + 3*u - 4*u^2 + 2*u^3 + u^4 - u^5 + u^6",
							"-1 + 3*u + 4*u^2 - 5*u^3 - 3*u^4 + 2*u^5 + u^6"
						],
						"aCuspShape":"-24 + 10*u + 30*u^2 - 9*u^3 - 11*u^4 + 4*u^5",
						"RepresentationsN":[
							[
								"u->-1.12314 + 0.280028 I",
								"a->-0.484226 + 0.358962 I",
								"b->-0.515774 - 0.358962 I"
							],
							[
								"u->-1.12314 - 0.280028 I",
								"a->-0.484226 - 0.358962 I",
								"b->-0.515774 + 0.358962 I"
							],
							[
								"u->0.779219",
								"a->-1.85322",
								"b->0.853215"
							],
							[
								"u->-0.272443",
								"a->-2.53061",
								"b->1.53061"
							],
							[
								"u->1.86975 + 0.14034 I",
								"a->0.176141 - 0.745556 I",
								"b->-1.17614 + 0.745556 I"
							],
							[
								"u->1.86975 - 0.14034 I",
								"a->0.176141 + 0.745556 I",
								"b->-1.17614 - 0.745556 I"
							]
						],
						"Epsilon":1.15952,
						"uPolys_ij":[
							"-1 + 3*u + 4*u^2 - 5*u^3 - 3*u^4 + 2*u^5 + u^6",
							"-1 - 3*u + 4*u^2 + 5*u^3 - 3*u^4 - 2*u^5 + u^6",
							"1 + 17*u + 52*u^2 + 63*u^3 + 37*u^4 + 10*u^5 + u^6",
							"1 - 17*u + 52*u^2 - 63*u^3 + 37*u^4 - 10*u^5 + u^6",
							"-9 - 3*u + 40*u^2 - 34*u^3 - 2*u^4 + 6*u^5 + u^6",
							"1 - u - 2*u^2 + 4*u^3 - 2*u^5 + u^6",
							"-1 - u + 11*u^2 + 2*u^3 + 22*u^4 + 9*u^5 + u^6",
							"1 - u + 2*u^2 - 8*u^3 - 3*u^4 + u^5 + u^6",
							"83 - 265*u + 284*u^2 - 97*u^3 - 12*u^4 + 7*u^5 + u^6",
							"-1 + u + 11*u^2 - 2*u^3 + 22*u^4 - 9*u^5 + u^6",
							"-1 + 4*u - 3*u^2 - 4*u^3 + 2*u^4 + u^6",
							"1 - 2*u + 4*u^3 - 2*u^4 - u^5 + u^6",
							"23 + 73*u - 88*u^2 - 10*u^3 + 35*u^4 - 11*u^5 + u^6",
							"-9 - 24*u - 26*u^2 - 11*u^3 + 4*u^4 + 4*u^5 + u^6",
							"-7 + 17*u - 6*u^2 - 8*u^3 + 2*u^5 + u^6",
							"-1 + 12*u^2 - 24*u^3 + 17*u^4 - 6*u^5 + u^6",
							"7 + 65*u + 122*u^2 + 69*u^3 - u^4 - 6*u^5 + u^6",
							"1 - 15*u + 21*u^2 - 12*u^3 - 6*u^4 + 3*u^5 + u^6",
							"1 - 3*u + 5*u^2 - 6*u^3 + 8*u^4 - 5*u^5 + u^6",
							"-1 + 12*u - 29*u^2 - 24*u^3 + 93*u^4 + 12*u^5 + u^6",
							"-23 - 51*u + u^2 - 30*u^3 + 26*u^4 - 5*u^5 + u^6",
							"9 + 42*u - 73*u^2 - 12*u^3 + 45*u^4 + 11*u^5 + u^6",
							"13 - 11*u - 18*u^2 + 18*u^3 - 2*u^5 + u^6",
							"-1 - 5*u - 5*u^2 + 2*u^4 + u^5 + u^6",
							"1 - 4*u + 12*u^2 - 18*u^3 + 12*u^4 - 5*u^5 + u^6",
							"-1 + 3*u - 4*u^2 + 2*u^3 + u^4 - u^5 + u^6",
							"-7 + 2*u + 21*u^2 - 32*u^3 + 21*u^4 - 7*u^5 + u^6",
							"-13 + 15*u - 16*u^2 + 2*u^3 + 10*u^4 - 6*u^5 + u^6",
							"-29 - 28*u + 23*u^2 + 20*u^3 - 7*u^4 - 3*u^5 + u^6",
							"59 - 187*u + 198*u^2 - 68*u^3 - 10*u^4 + 6*u^5 + u^6",
							"1 - 10*u + 37*u^2 - 30*u^3 - 2*u^4 + 4*u^5 + u^6",
							"1 - 7*u + 11*u^2 - 12*u^3 + 5*u^4 + u^6",
							"7 + 41*u + 86*u^2 + 86*u^3 + 41*u^4 + 9*u^5 + u^6",
							"-59 + 148*u - 25*u^2 - 103*u^3 + 46*u^4 + 15*u^5 + u^6",
							"-23 + 26*u + 34*u^2 - 73*u^3 + 24*u^4 + 12*u^5 + u^6",
							"-1 - 3*u - 4*u^2 - 2*u^3 + u^4 + u^5 + u^6",
							"-1 + 5*u - 5*u^2 + 2*u^4 - u^5 + u^6",
							"9 + 6*u - 5*u^2 + 4*u^3 + 6*u^4 + 2*u^5 + u^6",
							"-64 + 64*u - 16*u^2 - 64*u^3 + 44*u^4 + 6*u^5 + u^6",
							"7 - 51*u + 123*u^2 - 138*u^3 + 63*u^4 - 6*u^5 + u^6",
							"1 - 46*u + 116*u^2 - 107*u^3 + 40*u^4 - 6*u^5 + u^6",
							"-223 - 467*u - 247*u^2 + 92*u^3 + 98*u^4 + 13*u^5 + u^6"
						],
						"GeometricComponent":0,
						"uPolys_ij_N":[
							"-1 + 3*u + 4*u^2 - 5*u^3 - 3*u^4 + 2*u^5 + u^6",
							"-1 - 3*u + 4*u^2 + 5*u^3 - 3*u^4 - 2*u^5 + u^6",
							"1 + 17*u + 52*u^2 + 63*u^3 + 37*u^4 + 10*u^5 + u^6",
							"1 - 17*u + 52*u^2 - 63*u^3 + 37*u^4 - 10*u^5 + u^6",
							"-9 - 3*u + 40*u^2 - 34*u^3 - 2*u^4 + 6*u^5 + u^6",
							"1 - u - 2*u^2 + 4*u^3 - 2*u^5 + u^6",
							"-1 - u + 11*u^2 + 2*u^3 + 22*u^4 + 9*u^5 + u^6",
							"1 - u + 2*u^2 - 8*u^3 - 3*u^4 + u^5 + u^6",
							"83 - 265*u + 284*u^2 - 97*u^3 - 12*u^4 + 7*u^5 + u^6",
							"-1 + u + 11*u^2 - 2*u^3 + 22*u^4 - 9*u^5 + u^6",
							"-1 + 4*u - 3*u^2 - 4*u^3 + 2*u^4 + u^6",
							"1 - 2*u + 4*u^3 - 2*u^4 - u^5 + u^6",
							"23 + 73*u - 88*u^2 - 10*u^3 + 35*u^4 - 11*u^5 + u^6",
							"-9 - 24*u - 26*u^2 - 11*u^3 + 4*u^4 + 4*u^5 + u^6",
							"-7 + 17*u - 6*u^2 - 8*u^3 + 2*u^5 + u^6",
							"-1 + 12*u^2 - 24*u^3 + 17*u^4 - 6*u^5 + u^6",
							"7 + 65*u + 122*u^2 + 69*u^3 - u^4 - 6*u^5 + u^6",
							"1 - 15*u + 21*u^2 - 12*u^3 - 6*u^4 + 3*u^5 + u^6",
							"1 - 3*u + 5*u^2 - 6*u^3 + 8*u^4 - 5*u^5 + u^6",
							"-1 + 12*u - 29*u^2 - 24*u^3 + 93*u^4 + 12*u^5 + u^6",
							"-23 - 51*u + u^2 - 30*u^3 + 26*u^4 - 5*u^5 + u^6",
							"9 + 42*u - 73*u^2 - 12*u^3 + 45*u^4 + 11*u^5 + u^6",
							"13 - 11*u - 18*u^2 + 18*u^3 - 2*u^5 + u^6",
							"-1 - 5*u - 5*u^2 + 2*u^4 + u^5 + u^6",
							"1 - 4*u + 12*u^2 - 18*u^3 + 12*u^4 - 5*u^5 + u^6",
							"-1 + 3*u - 4*u^2 + 2*u^3 + u^4 - u^5 + u^6",
							"-7 + 2*u + 21*u^2 - 32*u^3 + 21*u^4 - 7*u^5 + u^6",
							"-13 + 15*u - 16*u^2 + 2*u^3 + 10*u^4 - 6*u^5 + u^6",
							"-29 - 28*u + 23*u^2 + 20*u^3 - 7*u^4 - 3*u^5 + u^6",
							"59 - 187*u + 198*u^2 - 68*u^3 - 10*u^4 + 6*u^5 + u^6",
							"1 - 10*u + 37*u^2 - 30*u^3 - 2*u^4 + 4*u^5 + u^6",
							"1 - 7*u + 11*u^2 - 12*u^3 + 5*u^4 + u^6",
							"7 + 41*u + 86*u^2 + 86*u^3 + 41*u^4 + 9*u^5 + u^6",
							"-59 + 148*u - 25*u^2 - 103*u^3 + 46*u^4 + 15*u^5 + u^6",
							"-23 + 26*u + 34*u^2 - 73*u^3 + 24*u^4 + 12*u^5 + u^6",
							"-1 - 3*u - 4*u^2 - 2*u^3 + u^4 + u^5 + u^6",
							"-1 + 5*u - 5*u^2 + 2*u^4 - u^5 + u^6",
							"9 + 6*u - 5*u^2 + 4*u^3 + 6*u^4 + 2*u^5 + u^6",
							"-64 + 64*u - 16*u^2 - 64*u^3 + 44*u^4 + 6*u^5 + u^6",
							"7 - 51*u + 123*u^2 - 138*u^3 + 63*u^4 - 6*u^5 + u^6",
							"1 - 46*u + 116*u^2 - 107*u^3 + 40*u^4 - 6*u^5 + u^6",
							"-223 - 467*u - 247*u^2 + 92*u^3 + 98*u^4 + 13*u^5 + u^6"
						],
						"Multiplicity":1,
						"ij_list":[
							[
								"{1, 9}",
								"{1, 10}",
								"{2, 11}",
								"{3, 12}"
							],
							[
								"{8, 12}",
								"{9, 12}"
							],
							[
								"{8, 9}",
								"{9, 10}"
							],
							[
								"{1, 12}",
								"{5, 9}"
							],
							[
								"{3, 11}"
							],
							[
								"{2, 12}"
							],
							[
								"{10, 12}"
							],
							[
								"{6, 7}",
								"{11, 12}"
							],
							[
								"{5, 7}"
							],
							[
								"{1, 8}"
							],
							[
								"{1, 4}",
								"{2, 4}",
								"{4, 10}",
								"{4, 11}",
								"{5, 11}"
							],
							[
								"{3, 7}",
								"{3, 8}",
								"{4, 8}"
							],
							[
								"{3, 9}"
							],
							[
								"{6, 10}"
							],
							[
								"{1, 6}"
							],
							[
								"{4, 7}"
							],
							[
								"{8, 10}"
							],
							[
								"{2, 3}",
								"{5, 6}"
							],
							[
								"{4, 6}",
								"{6, 8}"
							],
							[
								"{5, 10}"
							],
							[
								"{7, 9}"
							],
							[
								"{1, 5}"
							],
							[
								"{1, 11}"
							],
							[
								"{9, 11}"
							],
							[
								"{3, 4}",
								"{6, 9}",
								"{7, 8}"
							],
							[
								"{4, 12}"
							],
							[
								"{2, 9}"
							],
							[
								"{2, 8}"
							],
							[
								"{8, 11}"
							],
							[
								"{2, 10}"
							],
							[
								"{1, 2}",
								"{4, 5}",
								"{10, 11}"
							],
							[
								"{5, 12}"
							],
							[
								"{7, 11}"
							],
							[
								"{3, 10}"
							],
							[
								"{1, 3}"
							],
							[
								"{6, 11}",
								"{6, 12}",
								"{7, 12}"
							],
							[
								"{2, 5}",
								"{2, 6}",
								"{3, 6}",
								"{4, 9}"
							],
							[
								"{2, 7}"
							],
							[
								"{1, 7}"
							],
							[
								"{3, 5}"
							],
							[
								"{5, 8}"
							],
							[
								"{7, 10}"
							]
						],
						"SortedReprnIndices":"{5, 6, 2, 1, 4, 3}",
						"aCuspShapeN":[
							"-3.2532476149870296385`5.121580858184058 - 1.2282108669854998995`4.698536673736091*I",
							"-3.2532476149870296385`5.121580858184058 + 1.2282108669854998995`4.698536673736091*I",
							-5.1568,
							-2.4382e1,
							"-2.4772224026489299626`5.016171039794653 - 2.2925618198784685416`4.982527096347261*I",
							"-2.4772224026489299626`5.016171039794653 + 2.2925618198784685416`4.982527096347261*I"
						],
						"Abelian":false
					},
					{
						"IdealName":"abJ12n_749_2",
						"Generators":[
							"b",
							"-1 + a",
							"-1 + v"
						],
						"VariableOrder":[
							"b",
							"a",
							"v"
						],
						"Characteristic":0,
						"KnownGroebner":[],
						"Status":[
							"vCompNormalize"
						],
						"MonomialOrder":"lex",
						"IsHomogeneous":false,
						"IsZeroDim":true,
						"IdealDimension":0,
						"Timings":{
							"TimingGroebner":0.168453,
							"TimingZeroDimVars":0.480891,
							"TimingmagmaVCompNormalize":0.48222,
							"TimingNumberOfSols":0.258248,
							"TimingIsRadical":2.0069e-2,
							"TimingArcColoring":0.742264,
							"TimingObstruction":4.5599999999999997e-4,
							"TimingComplexVolumeN":0.595268,
							"TimingaCuspShapeN":5.278e-3,
							"TiminguValues":0.767384,
							"TiminguPolysN":8.300000000000001e-5,
							"TiminguPolys":0.983339,
							"TimingaCuspShape":9.5655e-2,
							"TimingRepresentationsN":2.3953000000000002e-2,
							"TiminguValues_ij":1.306845,
							"TiminguPoly_ij":1.488731,
							"TiminguPolys_ij_N":4.3e-5
						},
						"ZeroDimensionalVars":[
							"b",
							"a",
							"v"
						],
						"NumberOfSols":1,
						"IsRadical":true,
						"ArcColoring":[
							"{1, 0}",
							"{1, 0}",
							"{1, 0}",
							"{1, 0}",
							"{1, 0}",
							"{1, 0}",
							"{1, 0}",
							"{1, 0}",
							"{1, 0}",
							"{1, 0}",
							"{1, 0}",
							"{1, 0}"
						],
						"Obstruction":1,
						"ComplexVolumeN":"{0}",
						"uPolysN":[
							"u",
							"u",
							"u",
							"u",
							"u",
							"u",
							"u",
							"u",
							"u",
							"u",
							"u",
							"u"
						],
						"uPolys":[
							"u",
							"u",
							"u",
							"u",
							"u",
							"u",
							"u",
							"u",
							"u",
							"u",
							"u",
							"u"
						],
						"aCuspShape":0,
						"RepresentationsN":[
							[
								"v->1.",
								"a->1.",
								"b->0"
							]
						],
						"Epsilon":"Infinity",
						"uPolys_ij":[
							"u"
						],
						"GeometricComponent":0,
						"uPolys_ij_N":[
							"u"
						],
						"Multiplicity":1,
						"ij_list":[
							[
								"{1, 2}",
								"{1, 3}",
								"{1, 4}",
								"{1, 5}",
								"{1, 6}",
								"{1, 7}",
								"{1, 8}",
								"{1, 9}",
								"{1, 10}",
								"{1, 11}",
								"{1, 12}",
								"{2, 3}",
								"{2, 4}",
								"{2, 5}",
								"{2, 6}",
								"{2, 7}",
								"{2, 8}",
								"{2, 9}",
								"{2, 10}",
								"{2, 11}",
								"{2, 12}",
								"{3, 4}",
								"{3, 5}",
								"{3, 6}",
								"{3, 7}",
								"{3, 8}",
								"{3, 9}",
								"{3, 10}",
								"{3, 11}",
								"{3, 12}",
								"{4, 5}",
								"{4, 6}",
								"{4, 7}",
								"{4, 8}",
								"{4, 9}",
								"{4, 10}",
								"{4, 11}",
								"{4, 12}",
								"{5, 6}",
								"{5, 7}",
								"{5, 8}",
								"{5, 9}",
								"{5, 10}",
								"{5, 11}",
								"{5, 12}",
								"{6, 7}",
								"{6, 8}",
								"{6, 9}",
								"{6, 10}",
								"{6, 11}",
								"{6, 12}",
								"{7, 8}",
								"{7, 9}",
								"{7, 10}",
								"{7, 11}",
								"{7, 12}",
								"{8, 9}",
								"{8, 10}",
								"{8, 11}",
								"{8, 12}",
								"{9, 10}",
								"{9, 11}",
								"{9, 12}",
								"{10, 11}",
								"{10, 12}",
								"{11, 12}"
							]
						],
						"SortedReprnIndices":"{1}",
						"aCuspShapeN":"{0}",
						"Abelian":true
					}
				]
			},
			"uPolyC":[
				"(-1 + 4*u - 3*u^2 - 4*u^3 + 2*u^4 + u^6)*(-1 - 2*u - 4*u^2 - 13*u^3 + 3*u^4 - 15*u^5 + 15*u^6 + 18*u^7 - u^8 + u^9)",
				"(-1 + 5*u - 5*u^2 + 2*u^4 - u^5 + u^6)*(1 - 7*u + 10*u^2 + 30*u^3 - 72*u^4 + 42*u^5 - 31*u^6 + 15*u^7 + u^9)",
				"(1 - 2*u + 4*u^3 - 2*u^4 - u^5 + u^6)*(8 - 20*u + 8*u^2 + 57*u^3 - 132*u^4 + 144*u^5 - 94*u^6 + 38*u^7 - 9*u^8 + u^9)",
				"(-1 + 4*u - 3*u^2 - 4*u^3 + 2*u^4 + u^6)*(-1 - 2*u - 4*u^2 - 13*u^3 + 3*u^4 - 15*u^5 + 15*u^6 + 18*u^7 - u^8 + u^9)",
				"(-1 - 5*u - 5*u^2 + 2*u^4 + u^5 + u^6)*(1 - 7*u + 10*u^2 + 30*u^3 - 72*u^4 + 42*u^5 - 31*u^6 + 15*u^7 + u^9)",
				"(-1 - 3*u - 4*u^2 - 2*u^3 + u^4 + u^5 + u^6)*(-1 - u + 11*u^2 + 8*u^3 + 14*u^4 + 39*u^5 + 4*u^6 + 12*u^7 + 2*u^8 + u^9)",
				"(1 + 2*u - 4*u^3 - 2*u^4 + u^5 + u^6)*(8 - 20*u + 8*u^2 + 57*u^3 - 132*u^4 + 144*u^5 - 94*u^6 + 38*u^7 - 9*u^8 + u^9)",
				"(-1 - 3*u + 4*u^2 + 5*u^3 - 3*u^4 - 2*u^5 + u^6)*(-1 - 5*u + 5*u^2 + 15*u^3 - 22*u^4 - 3*u^5 + 15*u^6 - 3*u^7 - 3*u^8 + u^9)",
				"(-1 - 3*u + 4*u^2 + 5*u^3 - 3*u^4 - 2*u^5 + u^6)*(-1 - 5*u + 5*u^2 + 15*u^3 - 22*u^4 - 3*u^5 + 15*u^6 - 3*u^7 - 3*u^8 + u^9)",
				"(-1 - 4*u - 3*u^2 + 4*u^3 + 2*u^4 + u^6)*(-1 - 2*u - 4*u^2 - 13*u^3 + 3*u^4 - 15*u^5 + 15*u^6 + 18*u^7 - u^8 + u^9)",
				"(-1 + 3*u - 4*u^2 + 2*u^3 + u^4 - u^5 + u^6)*(-1 - u + 11*u^2 + 8*u^3 + 14*u^4 + 39*u^5 + 4*u^6 + 12*u^7 + 2*u^8 + u^9)",
				"(-1 + 3*u + 4*u^2 - 5*u^3 - 3*u^4 + 2*u^5 + u^6)*(-1 - 5*u + 5*u^2 + 15*u^3 - 22*u^4 - 3*u^5 + 15*u^6 - 3*u^7 - 3*u^8 + u^9)"
			],
			"RileyPolyC":[
				"(1 - 10*y + 37*y^2 - 30*y^3 - 2*y^4 + 4*y^5 + y^6)*(-1 - 4*y + 42*y^2 + 283*y^3 + 427*y^4 - 345*y^5 - 785*y^6 + 324*y^7 + 35*y^8 + y^9)",
				"(1 - 15*y + 21*y^2 - 12*y^3 - 6*y^4 + 3*y^5 + y^6)*(-1 + 29*y - 376*y^2 + 1814*y^3 - 2254*y^4 - 1814*y^5 + 359*y^6 + 309*y^7 + 30*y^8 + y^9)",
				"(1 - 4*y + 12*y^2 - 18*y^3 + 12*y^4 - 5*y^5 + y^6)*(-64 + 272*y - 232*y^2 + 1105*y^3 - 880*y^4 + 356*y^5 - 154*y^6 + 40*y^7 - 5*y^8 + y^9)",
				"(1 - 10*y + 37*y^2 - 30*y^3 - 2*y^4 + 4*y^5 + y^6)*(-1 - 4*y + 42*y^2 + 283*y^3 + 427*y^4 - 345*y^5 - 785*y^6 + 324*y^7 + 35*y^8 + y^9)",
				"(1 - 15*y + 21*y^2 - 12*y^3 - 6*y^4 + 3*y^5 + y^6)*(-1 + 29*y - 376*y^2 + 1814*y^3 - 2254*y^4 - 1814*y^5 + 359*y^6 + 309*y^7 + 30*y^8 + y^9)",
				"(1 - y + 2*y^2 - 8*y^3 - 3*y^4 + y^5 + y^6)*(-1 + 23*y - 109*y^2 - 314*y^3 + 320*y^4 + 1555*y^5 + 880*y^6 + 206*y^7 + 20*y^8 + y^9)",
				"(1 - 4*y + 12*y^2 - 18*y^3 + 12*y^4 - 5*y^5 + y^6)*(-64 + 272*y - 232*y^2 + 1105*y^3 - 880*y^4 + 356*y^5 - 154*y^6 + 40*y^7 - 5*y^8 + y^9)",
				"(1 - 17*y + 52*y^2 - 63*y^3 + 37*y^4 - 10*y^5 + y^6)*(-1 + 35*y - 219*y^2 + 505*y^3 - 700*y^4 + 599*y^5 - 309*y^6 + 93*y^7 - 15*y^8 + y^9)",
				"(1 - 17*y + 52*y^2 - 63*y^3 + 37*y^4 - 10*y^5 + y^6)*(-1 + 35*y - 219*y^2 + 505*y^3 - 700*y^4 + 599*y^5 - 309*y^6 + 93*y^7 - 15*y^8 + y^9)",
				"(1 - 10*y + 37*y^2 - 30*y^3 - 2*y^4 + 4*y^5 + y^6)*(-1 - 4*y + 42*y^2 + 283*y^3 + 427*y^4 - 345*y^5 - 785*y^6 + 324*y^7 + 35*y^8 + y^9)",
				"(1 - y + 2*y^2 - 8*y^3 - 3*y^4 + y^5 + y^6)*(-1 + 23*y - 109*y^2 - 314*y^3 + 320*y^4 + 1555*y^5 + 880*y^6 + 206*y^7 + 20*y^8 + y^9)",
				"(1 - 17*y + 52*y^2 - 63*y^3 + 37*y^4 - 10*y^5 + y^6)*(-1 + 35*y - 219*y^2 + 505*y^3 - 700*y^4 + 599*y^5 - 309*y^6 + 93*y^7 - 15*y^8 + y^9)"
			]
		},
		"GeometricRepresentation":[
			5.9861,
			[
				"J12n_749_0",
				1,
				"{8, 9}"
			]
		]
	},
	"Hyperbolic":true
}